ParticlePhaseSpace/DataExporters.py
ParticlePhaseSpace/DataLoaders.py
ParticlePhaseSpace/_ParticlePhaseSpace.py
ParticlePhaseSpace/__init__.py
ParticlePhaseSpace/__particle_config__.py
ParticlePhaseSpace/__phase_space_config__.py
ParticlePhaseSpace/__unit_config__.py
ParticlePhaseSpace/utilities.py
particlephasespace-0.8.0.dist-info/METADATA
particlephasespace-0.8.0.dist-info/WHEEL
particlephasespace-0.8.0.dist-info/licenses/LICENSE
particlephasespace-0.8.0.dist-info/RECORD
