Metadata-Version: 2.4
Name: particlephasespace
Version: 0.8.0
Summary: Import, analysis, and export of particle phase space data
License: GPL3
License-File: LICENSE
Author: Brendan
Author-email: bwheelz360@gmail.com
Requires-Python: >=3.9,<4.0
Classifier: License :: Other/Proprietary License
Classifier: Programming Language :: Python :: 3
Classifier: Programming Language :: Python :: 3.9
Classifier: Programming Language :: Python :: 3.10
Classifier: Programming Language :: Python :: 3.11
Classifier: Programming Language :: Python :: 3.12
Classifier: Programming Language :: Python :: 3.13
Classifier: Programming Language :: Python :: 3.14
Requires-Dist: matplotlib (>=3.9.0,<4.0.0)
Requires-Dist: numpy (>=2.0.0,<3.0.0)
Requires-Dist: pandas (>=2.2.2,<3.0.0)
Requires-Dist: scipy (>=1.13.0,<2.0.0)
Requires-Dist: topas2numpy (>=0.2.0,<0.3.0)
